hikari_core/__init__.py
hikari_core/analyze.py
hikari_core/cache_utils.py
hikari_core/command_select.py
hikari_core/config.py
hikari_core/data_source.py
hikari_core/game/__init__.py
hikari_core/game/ban_search.py
hikari_core/game/box_check.py
hikari_core/game/help.py
hikari_core/game/roll.py
hikari_core/game/sx.py
hikari_core/Html_Render/__init__.py
hikari_core/Html_Render/browser.py
hikari_core/Html_Render/data_source.py
hikari_core/Html_Render/minimal_screens_hot_service.py
hikari_core/Html_Render/templates/github-markdown-light.css
hikari_core/Html_Render/templates/markdown.html
hikari_core/Html_Render/templates/pygments-default.css
hikari_core/Html_Render/templates/text.css
hikari_core/Html_Render/templates/text.html
hikari_core/HttpClient_Pool.py
hikari_core/model.py
hikari_core/moudle/__init__.py
hikari_core/moudle/publicAPI.py
hikari_core/moudle/wws_bind.py
hikari_core/moudle/wws_clan.py
hikari_core/moudle/wws_clanrank.py
hikari_core/moudle/wws_cw_recent.py
hikari_core/moudle/wws_cwrank.py
hikari_core/moudle/wws_info.py
hikari_core/moudle/wws_real_game.py
hikari_core/moudle/wws_recent.py
hikari_core/moudle/wws_recents.py
hikari_core/moudle/wws_ship_info.py
hikari_core/moudle/wws_ship_recent.py
hikari_core/moudle/wws_shiprank.py
hikari_core/Template/bind-list.html
hikari_core/Template/cw-rank.html
hikari_core/Template/select-clan.html
hikari_core/Template/select-ship-v2.html
hikari_core/Template/select-ship-v3.html
hikari_core/Template/select-ship.html
hikari_core/Template/ship-rank.html
hikari_core/Template/wws-ban.html
hikari_core/Template/wws-box-christmas-v2.html
hikari_core/Template/wws-box-christmas.html
hikari_core/Template/wws-clan-cw.html
hikari_core/Template/wws-clan.html
hikari_core/Template/wws-info-recent.html
hikari_core/Template/wws-info-recents.html
hikari_core/Template/wws-info.html
hikari_core/Template/wws-personalRecord.html
hikari_core/Template/wws-ship-recent.html
hikari_core/Template/wws-ship.html
hikari_core/Template/wws-sx.html
hikari_core-1.2.5.dist-info/LICENSE
hikari_core-1.2.5.dist-info/METADATA
hikari_core-1.2.5.dist-info/WHEEL
hikari_core-1.2.5.dist-info/RECORD
