Metadata-Version: 2.1
Name: hikari-core
Version: 1.2.5
Summary: SDK for yuyuko,战舰世界yuyuko平台BOT SDK
Home-page: https://github.com/wows-yuyuko/Hikari-core
Keywords: qqbot,wows,wws,bot,stats
Author: benx1n
Author-email: 1119809439@qq.com
Requires-Python: >=3.8,<4.0
Classifier: Programming Language :: Python :: 3
Classifier: Programming Language :: Python :: 3.8
Classifier: Programming Language :: Python :: 3.9
Classifier: Programming Language :: Python :: 3.10
Classifier: Programming Language :: Python :: 3.11
Requires-Dist: APScheduler (>=3.10.1,<4.0.0)
Requires-Dist: aiofiles (>=0.8.0)
Requires-Dist: asyncio (>=3.4.3,<4.0.0)
Requires-Dist: beautifulsoup4 (>=4.12.2,<5.0.0)
Requires-Dist: httpx[http2] (>=0.24.0)
Requires-Dist: jinja2 (>=3.0.0,<4.0.0)
Requires-Dist: json_tools (>=0.4.1,<0.5.0)
Requires-Dist: loguru (>=0.7.0,<0.8.0)
Requires-Dist: orjson (>=3.8.11,<4.0.0)
Requires-Dist: pillow (>=9.5.0,<10.0.0)
Requires-Dist: playwright (>=1.40.0)
Requires-Dist: pydantic (>=1.10.7,<2.0.0)
Requires-Dist: pytz (>=2025.2,<2026.0)
Project-URL: Repository, https://github.com/wows-yuyuko/Hikari-core
